geci_caller/__init__.py
geci_caller/call_api.py
geci_caller/cli.py
geci_caller-0.19.0.dist-info/entry_points.txt
geci_caller-0.19.0.dist-info/licenses/LICENSE
geci_caller-0.19.0.dist-info/WHEEL
geci_caller-0.19.0.dist-info/METADATA
geci_caller-0.19.0.dist-info/RECORD
