Metadata-Version: 2.4
Name: geci_caller
Version: 0.19.0
Summary: A template Python module
Home-page: https://github.com/IslasGECI/api_caller
Author: Ciencia de Datos • GECI
Author-email: ciencia.datos@islas.org.mx
Requires-Python: >=3.9
Classifier: License :: OSI Approved :: GNU General Public License v3 or later (GPLv3+)
License-File: LICENSE
Requires-Dist: pandas
Requires-Dist: pandas-stubs
Requires-Dist: requests
Requires-Dist: requests_mock
Requires-Dist: typer[all]
Requires-Dist: types-requests
